{
  "$schema": "https://json-structure.org/meta/core/v0/#",
  "$id": "https://raw.githubusercontent.com/api-evangelist/adyen/refs/heads/main/json-structure/checkout-service-error-details-structure.json",
  "description": "ServiceErrorDetails schema from Adyen API",
  "type": "object",
  "properties": {
    "errorCode": {
      "type": "string"
    },
    "errorType": {
      "type": "string"
    },
    "message": {
      "type": "string"
    },
    "pspReference": {
      "type": "string"
    }
  },
  "name": "ServiceErrorDetails"
}