{
  "operationId": "get-grants",
  "method": "GET",
  "path": "/grants",
  "summary": "Adyen Get a Capital Account",
  "requestExamples": [],
  "responseExamples": [
    {
      "status": "200",
      "contentType": "application/json",
      "name": "get-grants200Example",
      "example": {
        "grants": [
          "example_value"
        ]
      }
    },
    {
      "status": "400",
      "contentType": "application/json",
      "name": "get-grants400Example",
      "example": {
        "detail": "example_value",
        "errorCode": "CODE123",
        "instance": "example_value",
        "invalidFields": [
          "example_value"
        ],
        "requestId": "500123",
        "response": "example_value",
        "status": 500,
        "title": "example_value",
        "type": "standard"
      }
    },
    {
      "status": "401",
      "contentType": "application/json",
      "name": "get-grants401Example",
      "example": {
        "detail": "example_value",
        "errorCode": "CODE123",
        "instance": "example_value",
        "invalidFields": [
          "example_value"
        ],
        "requestId": "500123",
        "response": "example_value",
        "status": 500,
        "title": "example_value",
        "type": "standard"
      }
    },
    {
      "status": "403",
      "contentType": "application/json",
      "name": "get-grants403Example",
      "example": {
        "detail": "example_value",
        "errorCode": "CODE123",
        "instance": "example_value",
        "invalidFields": [
          "example_value"
        ],
        "requestId": "500123",
        "response": "example_value",
        "status": 500,
        "title": "example_value",
        "type": "standard"
      }
    },
    {
      "status": "404",
      "contentType": "application/json",
      "name": "get-grants404Example",
      "example": {
        "detail": "example_value",
        "errorCode": "CODE123",
        "instance": "example_value",
        "invalidFields": [
          "example_value"
        ],
        "requestId": "500123",
        "response": "example_value",
        "status": 500,
        "title": "example_value",
        "type": "standard"
      }
    },
    {
      "status": "422",
      "contentType": "application/json",
      "name": "get-grants422Example",
      "example": {
        "detail": "example_value",
        "errorCode": "CODE123",
        "instance": "example_value",
        "invalidFields": [
          "example_value"
        ],
        "requestId": "500123",
        "response": "example_value",
        "status": 500,
        "title": "example_value",
        "type": "standard"
      }
    },
    {
      "status": "500",
      "contentType": "application/json",
      "name": "get-grants500Example",
      "example": {
        "detail": "example_value",
        "errorCode": "CODE123",
        "instance": "example_value",
        "invalidFields": [
          "example_value"
        ],
        "requestId": "500123",
        "response": "example_value",
        "status": 500,
        "title": "example_value",
        "type": "standard"
      }
    }
  ]
}