{
  "$schema": "https://json-schema.org/draft/2020-12/schema",
  "$id": "#/components/schemas/KYCPayoutMethodCheckResult",
  "title": "KYCPayoutMethodCheckResult",
  "properties": {
    "checks": {
      "description": "A list of the checks and their statuses.",
      "items": {
        "$ref": "#/components/schemas/KYCCheckStatusData"
      },
      "type": "array"
    },
    "payoutMethodCode": {
      "description": "The unique ID of the payoput method to which the check applies.",
      "type": "string"
    }
  },
  "type": "object"
}